<Invoice xmlns="urn:oasis:names:specification:ubl:schema:xsd:Invoice-2" xmlns:cac="urn:oasis:names:specification:ubl:schema:xsd:CommonAggregateComponents-2" xmlns:cbc="urn:oasis:names:specification:ubl:schema:xsd:CommonBasicComponents-2">
<cbc:ID>f9de271b-48dc-4ff9-9fec-3c3dcdf041e4</cbc:ID>
<cbc:IssueDate>2025-12-06</cbc:IssueDate>
<cbc:InvoiceTypeCode>380</cbc:InvoiceTypeCode>
<cbc:DocumentCurrencyCode>SDG</cbc:DocumentCurrencyCode>
<cac:AccountingSupplierParty>
<cac:Party>
<cbc:Name>My Supplier</cbc:Name>
<cac:PostalAddress>
<cbc:StreetName>Khartoum Bahri</cbc:StreetName>
<cbc:CityName>Khartoum</cbc:CityName>
<cbc:Country>
<cbc:IdentificationCode>SD</cbc:IdentificationCode>
</cbc:Country>
</cac:PostalAddress>
<cac:PartyTaxScheme>
<cbc:CompanyID>123456789</cbc:CompanyID>
<cac:TaxScheme>
<cbc:ID>VAT</cbc:ID>
</cac:TaxScheme>
</cac:PartyTaxScheme>
<cac:Contact>
<cbc:Telephone>+249912345678</cbc:Telephone>
<cbc:ElectronicMail>supplier@example.com</cbc:ElectronicMail>
</cac:Contact>
</cac:Party>
</cac:AccountingSupplierParty>
<cac:AccountingCustomerParty>
<cac:Party>
<cbc:Name>Default Customer</cbc:Name>
<cac:PostalAddress>
<cbc:StreetName>Omdurman</cbc:StreetName>
<cbc:CityName>Omdurman</cbc:CityName>
<cbc:Country>
<cbc:IdentificationCode>SD</cbc:IdentificationCode>
</cbc:Country>
</cac:PostalAddress>
<cac:PartyTaxScheme>
<cbc:CompanyID>5566778899</cbc:CompanyID>
<cac:TaxScheme>
<cbc:ID>VAT</cbc:ID>
</cac:TaxScheme>
</cac:PartyTaxScheme>
<cac:Contact>
<cbc:Telephone>+249911111111</cbc:Telephone>
<cbc:ElectronicMail>customer@example.com</cbc:ElectronicMail>
</cac:Contact>
</cac:Party>
</cac:AccountingCustomerParty>
<cac:InvoiceLine>
<cbc:ID>1</cbc:ID>
<cbc:InvoicedQuantity unitCode="EA">2.00</cbc:InvoicedQuantity>
<cbc:LineExtensionAmount currencyID="SDG">3000.00</cbc:LineExtensionAmount>
<cac:Item>
<cbc:Name>Laptop</cbc:Name>
<cbc:Description>Dell</cbc:Description>
</cac:Item>
<cac:Price>
<cbc:PriceAmount currencyID="SDG">1500.00</cbc:PriceAmount>
</cac:Price>
<cac:TaxTotal>
<cbc:TaxAmount currencyID="SDG">450.00</cbc:TaxAmount>
<cac:TaxSubtotal>
<cbc:TaxableAmount currencyID="SDG">3000.00</cbc:TaxableAmount>
<cbc:TaxAmount currencyID="SDG">450.00</cbc:TaxAmount>
<cac:TaxCategory>
<cbc:Percent>15.00</cbc:Percent>
<cac:TaxScheme>
<cbc:ID>VAT</cbc:ID>
</cac:TaxScheme>
</cac:TaxCategory>
</cac:TaxSubtotal>
</cac:TaxTotal>
</cac:InvoiceLine>
<cac:TaxTotal>
<cbc:TaxAmount currencyID="SDG">450.00</cbc:TaxAmount>
</cac:TaxTotal>
<cac:LegalMonetaryTotal>
<cbc:LineExtensionAmount currencyID="SDG">3000.00</cbc:LineExtensionAmount>
<cbc:TaxExclusiveAmount currencyID="SDG">3000.00</cbc:TaxExclusiveAmount>
<cbc:TaxInclusiveAmount currencyID="SDG">3450.00</cbc:TaxInclusiveAmount>
<cbc:PayableAmount currencyID="SDG">3450.00</cbc:PayableAmount>
</cac:LegalMonetaryTotal>
</Invoice>